flask_deta/__init__.py
flask_deta/deta_base.py
flask_deta/deta_drive.py
flask_deta/validator.py
flask_deta-0.2.1.dist-info/METADATA
flask_deta-0.2.1.dist-info/WHEEL
flask_deta-0.2.1.dist-info/licenses/LICENSE
flask_deta-0.2.1.dist-info/RECORD
