Metadata-Version: 2.1
Name: flask-deta
Version: 0.2.1
Summary: A Python library for seamless integration with DetaSpace in Flask
Project-URL: Homepage, https://flask-deta.readthedocs.io/en/latest/
Project-URL: Source Code, https://github.com/Jesparzarom/Flask-Deta
Project-URL: Bug Tracker, https://github.com/Jesparzarom/Flask-Deta/issues
Author: J.P. Esparza
Maintainer: J.P. Esparza
License: BSD-3 Clause License
License-File: LICENSE
Keywords: Databases,Deta,Detaspace,Drive,Fask Deta,Flask,Flask NoSQL,Flask Package,NoSQL,Python Deta,Web Development
Classifier: Development Status :: 3 - Alpha
Classifier: Framework :: Flask
Classifier: Intended Audience :: Developers
Classifier: Intended Audience :: End Users/Desktop
Classifier: License :: OSI Approved :: BSD License
Classifier: Operating System :: MacOS
Classifier: Operating System :: Microsoft
Classifier: Operating System :: POSIX
Classifier: Programming Language :: Python :: 3
Classifier: Topic :: Internet :: WWW/HTTP :: Dynamic Content
Classifier: Topic :: Software Development :: Libraries :: Python Modules
Requires-Python: >=3.10
Requires-Dist: deta>=1.2
Requires-Dist: flask>=2.3
